{
 "id": "cOkXdNtY6A4",
 "title": "【激怒】毎日ラーメン健康生活をパクる女子に先輩風吹かせに行ってみた結果。をすする　SUSURU TV.第3881回",
 "upload_date": "20260720",
 "description": "今回対決した「うに子」さん\n📷インスタ↓\nhttps://www.instagram.com/uniko_gurume/\n▶️YouTube↓\nhttps://www.youtube.com/@UCyF58zPVGo3R-C6AidZL5Fw \n\n\nうに子さんありがとうございました！！\nSUSURUは終始フワフワしてました。\n[編集：とし］\n\n【本日のお店】\nらーめん3000\n東京都豊島区駒込1-16-10 ルーブルビル 101号\nhttps://tabelog.com/tokyo/A1323/A132301/13308596/\n\n元祖スタミナ満点らーめん すず鬼\n東京都三鷹市下連雀3-28-21 公団三鷹駅前第2アパート B1F\nhttps://tabelog.com/tokyo/A1320/A132002/13241092/\n\n▼SUSURU WEB.▼\nラーメン情報を発信するWEBメディアを始めました。\nhttps://www.susurulab.co.jp/\n\n★SUSURU TV.の公式グッズサイト★\nSUSURUが動画内で着用しているTシャツ等\n数量限定品やコラボ商品も多数取り扱い中！\nhttps://shop.susurulab.co.jp/\n\nご視聴ありがとうございます。\nラーメンを毎日すする「毎日ラーメン健康生活」を実施中！\nチャンネル登録もよろしくお願いします！\n\n▼SUSURUのサブチャンネルもよろしく！▼\nhttps://www.youtube.com/@susurutv_sub\n\n■X（twitter）\nhttps://x.com/susuru_tv\n\n■instagram\nhttps://www.instagram.com/susuru_tv/\n\n\n◆ファンレター等の送り先はこちら\n〒166-0003\n東京都杉並区高円寺南1-12-2\nSUSURU宛　まで！\n※ここにSUSURUは住んでいません。近隣の方のご迷惑になりますので押しかけたりはご遠慮ください。\n\n■お仕事の依頼は■\ninfo@susurulab.co.jp\n企業様のお問い合わせは上記よりお願いいたします。\n\n\n#らーめん3000 #すず鬼 #うに子 #ラーメン  #毎日ラーメン生活",
 "duration": 1288,
 "view_count": 108774
}